tracing/__init__.py
tracing/_level.py
tracing/_store.py
tracing/_tracing.py
tracing_py3-0.1.1.dist-info/LICENSE
tracing_py3-0.1.1.dist-info/METADATA
tracing_py3-0.1.1.dist-info/WHEEL
tracing_py3-0.1.1.dist-info/RECORD
