Metadata-Version: 2.1
Name: tracing-py3
Version: 0.1.1
Summary: Superset of python internal logging module
Home-page: https://github.com/hendrikboeck/tracing-py3
License: MIT
Keywords: logging,monitoring,tracing,debugging,python,superset,module,library
Author: Hendrik Boeck
Author-email: hendrikboeck.dev@protonmail.com
Requires-Python: >=3.11,<4.0
Classifier: Development Status :: 2 - Pre-Alpha
Classifier: Environment :: Console
Classifier: Intended Audience :: Developers
Classifier: License :: OSI Approved :: MIT License
Classifier: Operating System :: MacOS
Classifier: Operating System :: Microsoft :: Windows
Classifier: Operating System :: OS Independent
Classifier: Operating System :: POSIX
Classifier: Programming Language :: Python :: 3
Classifier: Programming Language :: Python :: 3.11
Classifier: Programming Language :: Python :: 3.12
Classifier: Topic :: Software Development :: Libraries
Classifier: Topic :: Software Development :: Libraries :: Python Modules
Classifier: Topic :: System :: Logging
Classifier: Topic :: System :: Monitoring
Classifier: Typing :: Typed
Requires-Dist: basic-panic (>=0.1.0,<0.2.0)
Project-URL: Repository, https://github.com/hendrikboeck/tracing-py3
